Workbook
Name aporte: Planilha1!$D$18
Name patrimonio: Planilha1!$D$21
Name qtd_anos: Planilha1!$D$19
Name rendimento_carteira: Planilha1!$D$14
Name salario: Planilha1!$D$13
Name sugestao: Planilha1!$D$15
Name taxa_mensal: Planilha1!$D$20

Sheet Planilha1
B12: CONFIGURAÇÕES
B13: Salário | D13: 4200
B14: Rendimento Carteira | D14: 0.006
B15: Sugestão de Investimento (30%) | D15: =D13*30% -> 1260
B17: INVESTIMENTO MENSAL
B18: Quanto invertir por mês? | D18: 1260
B19: Por quanto tempo? | D19: 10
B20: Taxa de rendimento mensal? | D20: 0.01079
B21: Patrimônio Acumulado? | D21: =FV(taxa_mensal,qtd_anos*12,aporte*-1) -> 306538.11
B22: Dividendos mensais? | D22: =patrimonio*rendimento_carteira -> 1839.2286
B24: CENÁRIOS | D24: Dividendo
A25: 2 | B25: Em 2 anos | C25: =FV($D$20,$A25*12,$D$18*-1) -> 34306.81 | D25: =C25*rendimento_carteira -> 205.84086
A26: 5 | B26: Em 5 anos | C26: =FV($D$20,$A26*12,$D$18*-1) -> 105558.91 | D26: =C26*rendimento_carteira -> 633.35347
A27: 10 | B27: Em 10 anos | C27: =FV($D$20,$A27*12,$D$18*-1) -> 306538.11 | D27: =C27*rendimento_carteira -> 1839.2286
A28: 20 | B28: Em 20 anos | C28: =FV($D$20,$A28*12,$D$18*-1) -> 1417750 | D28: =C28*rendimento_carteira -> 8506.4999
A29: 30 | B29: em 30 anos | C29: =FV($D$20,$A29*12,$D$18*-1) -> 5445933.8 | D29: =C29*rendimento_carteira -> 32675.603
B32: PERFIL | C32: Agressivo
B33: Valor a ser investido por mês | C33: =aporte -> 1260
B35: TIPO DE FII | C35: Percentual Sugerido | D35: Valor
B36: PAPEL | C36: =$C$32&"-"&B36 -> Agressivo-PAPEL | D36: =VLOOKUP(C36,Planilha2!B3:E20,4,FALSE)*$C$33 -> 630
B37: TIJOLO | C37: =$C$32&"-"&B37 -> Agressivo-TIJOLO | D37: =VLOOKUP(C37,Planilha2!B4:E21,4,FALSE)*$C$33 -> 126
B38: HIBRIDOS | C38: =$C$32&"-"&B38 -> Agressivo-HIBRIDOS | D38: =VLOOKUP(C38,Planilha2!B5:E22,4,FALSE)*$C$33 -> 63
B39: FOFs | C39: =$C$32&"-"&B39 -> Agressivo-FOFs | D39: =VLOOKUP(C39,Planilha2!B6:E23,4,FALSE)*$C$33 -> 63
B40: DESENVOLVIMENTO | C40: =$C$32&"-"&B40 -> Agressivo-DESENVOLVIMENTO | D40: =VLOOKUP(C40,Planilha2!B7:E24,4,FALSE)*$C$33 -> 252
B41: HOTELARIAS | C41: =$C$32&"-"&B41 -> Agressivo-HOTELARIAS | D41: =VLOOKUP(C41,Planilha2!B8:E25,4,FALSE)*$C$33 -> 126
D42: =SUM(D36:D41) -> 1260

Sheet Planilha2
B2: CHAVE | C2: PERFIL | D2: TIPO FII | E2: %
B3: =C3&"-"&D3 -> Conservador-PAPEL | C3: Conservador | D3: PAPEL | E3: 0.3
B4: =C4&"-"&D4 -> Conservador-TIJOLO | C4: Conservador | D4: TIJOLO | E4: 0.5
B5: =C5&"-"&D5 -> Conservador-HIBRIDOS | C5: Conservador | D5: HIBRIDOS | E5: 0.1
B6: =C6&"-"&D6 -> Conservador-FOFs | C6: Conservador | D6: FOFs | E6: 0.1
B7: =C7&"-"&D7 -> Conservador-DESENVOLVIMENTO | C7: Conservador | D7: DESENVOLVIMENTO | E7: 0
B8: =C8&"-"&D8 -> Conservador-HOTELARIAS | C8: Conservador | D8: HOTELARIAS | E8: 0
B9: =C9&"-"&D9 -> Moderado-PAPEL | C9: Moderado | D9: PAPEL | E9: 0.32
B10: =C10&"-"&D10 -> Moderado-TIJOLO | C10: Moderado | D10: TIJOLO | E10: 0.35
B11: =C11&"-"&D11 -> Moderado-HIBRIDOS | C11: Moderado | D11: HIBRIDOS | E11: 0.08
B12: =C12&"-"&D12 -> Moderado-FOFs | C12: Moderado | D12: FOFs | E12: 0.05
B13: =C13&"-"&D13 -> Moderado-DESENVOLVIMENTO | C13: Moderado | D13: DESENVOLVIMENTO | E13: 0.1
B14: =C14&"-"&D14 -> Moderado-HOTELARIAS | C14: Moderado | D14: HOTELARIAS | E14: 0.1
... B20: =C20&"-"&D20 -> Agressivo-HOTELARIAS | C20: Agressivo | D20: HOTELARIAS | E20: 0.1
